[
  {
    "matchId": "g_3_GOxJBPLs",
    "eventTime": "21.11. 18:00",
    "homeTeam": "Szombathely",
    "awayTeam": "Peristeri"
  },
  {
    "matchId": "g_3_tfWfkxrR",
    "eventTime": "21.11. 18:30",
    "homeTeam": "VEF Riga",
    "awayTeam": "Cholet"
  },
  {
    "matchId": "g_3_SIfQoIK8",
    "eventTime": "21.11. 20:00",
    "homeTeam": "Bonn",
    "awayTeam": "Bursaspor"
  },
  {
    "matchId": "g_3_6mnuz04a",
    "eventTime": "21.11. 21:00",
    "homeTeam": "Tenerife",
    "awayTeam": "Darussafaka"
  },
  {
    "matchId": "g_3_v16ImJYb",
    "eventTime": "22.11. 18:30",
    "homeTeam": "AEK Athens",
    "awayTeam": "Szczecin"
  },
  {
    "matchId": "g_3_AspVpxzF",
    "eventTime": "22.11. 20:30",
    "homeTeam": "Breogan",
    "awayTeam": "Hapoel Holon"
  },
  {
    "matchId": "g_3_bmSNAqyl",
    "eventTime": "22.11. 20:30",
    "homeTeam": "Le Mans",
    "awayTeam": "Unicaja"
  },
  {
    "matchId": "g_3_YN5Mnwl5",
    "eventTime": "22.11. 20:30",
    "homeTeam": "Sassari",
    "awayTeam": "Ludwigsburg"
  },
  {
    "matchId": "g_3_OpA4ayk8",
    "eventTime": "28.11. 18:00",
    "homeTeam": "Galatasaray",
    "awayTeam": "Hapoel Jerusalem"
  },
  {
    "matchId": "g_3_OSf3mVeD",
    "eventTime": "28.11. 18:30",
    "homeTeam": "Igokea",
    "awayTeam": "Murcia"
  },
  {
    "matchId": "g_3_AL8fYbj9",
    "eventTime": "28.11. 20:00",
    "homeTeam": "Oldenburg",
    "awayTeam": "Oostende"
  },
  {
    "matchId": "g_3_0C2vOES1",
    "eventTime": "29.11. 18:00",
    "homeTeam": "Bursaspor",
    "awayTeam": "Hapoel Holon"
  },
  {
    "matchId": "g_3_lUrkyHXS",
    "eventTime": "29.11. 18:30",
    "homeTeam": "PAOK",
    "awayTeam": "Benfica"
  },
  {
    "matchId": "g_3_ht8WQS2n",
    "eventTime": "29.11. 18:30",
    "homeTeam": "Pinar Karsiyaka",
    "awayTeam": "Strasbourg"
  },
  {
    "matchId": "g_3_hpM5L0k6",
    "eventTime": "29.11. 20:00",
    "homeTeam": "Dijon",
    "awayTeam": "Opava"
  },
  {
    "matchId": "g_3_ALW0Mtz0",
    "eventTime": "29.11. 20:15",
    "homeTeam": "Rytas",
    "awayTeam": "Promitheas"
  },
  {
    "matchId": "g_3_xWroCEYD",
    "eventTime": "29.11. 20:30",
    "homeTeam": "Tortona",
    "awayTeam": "Tofas"
  },
  {
    "matchId": "g_3_CE4Qoc3B",
    "eventTime": "05.12. 18:30",
    "homeTeam": "AEK Athens",
    "awayTeam": "Sassari"
  },
  {
    "matchId": "g_3_pvoqZJJ5",
    "eventTime": "05.12. 18:30",
    "homeTeam": "VEF Riga",
    "awayTeam": "Tenerife"
  },
  {
    "matchId": "g_3_bZIMpdjr",
    "eventTime": "05.12. 20:00",
    "homeTeam": "Cholet",
    "awayTeam": "Darussafaka"
  },
  {
    "matchId": "g_3_I7mwqG4R",
    "eventTime": "06.12. 18:00",
    "homeTeam": "Bursaspor",
    "awayTeam": "Breogan"
  },
  {
    "matchId": "g_3_xvRR93jf",
    "eventTime": "06.12. 18:30",
    "homeTeam": "Peristeri",
    "awayTeam": "Le Mans"
  },
  {
    "matchId": "g_3_UkaVpHIH",
    "eventTime": "06.12. 18:30",
    "homeTeam": "Szczecin",
    "awayTeam": "Ludwigsburg"
  },
  {
    "matchId": "g_3_lYrZqdkL",
    "eventTime": "06.12. 20:00",
    "homeTeam": "Hapoel Holon",
    "awayTeam": "Bonn"
  },
  {
    "matchId": "g_3_6DVV8N50",
    "eventTime": "06.12. 20:30",
    "homeTeam": "Unicaja",
    "awayTeam": "Szombathely"
  },
  {
    "matchId": "g_3_GMskBYmK",
    "eventTime": "12.12. 18:00",
    "homeTeam": "Tofas",
    "awayTeam": "Igokea"
  },
  {
    "matchId": "g_3_WzL9KK4C",
    "eventTime": "12.12. 18:30",
    "homeTeam": "Opava",
    "awayTeam": "Rytas"
  },
  {
    "matchId": "g_3_0APDJvKI",
    "eventTime": "12.12. 18:30",
    "homeTeam": "Promitheas",
    "awayTeam": "Dijon"
  },
  {
    "matchId": "g_3_AH2yQnIh",
    "eventTime": "12.12. 20:30",
    "homeTeam": "Oostende",
    "awayTeam": "Strasbourg"
  },
  {
    "matchId": "g_3_2y98be4E",
    "eventTime": "13.12. 18:30",
    "homeTeam": "Hapoel Jerusalem",
    "awayTeam": "PAOK"
  },
  {
    "matchId": "g_3_lC7bXI5F",
    "eventTime": "13.12. 20:00",
    "homeTeam": "Oldenburg",
    "awayTeam": "Pinar Karsiyaka"
  },
  {
    "matchId": "g_3_OMZGWztp",
    "eventTime": "13.12. 20:30",
    "homeTeam": "Benfica",
    "awayTeam": "Galatasaray"
  },
  {
    "matchId": "g_3_YcxfAh3Q",
    "eventTime": "13.12. 20:30",
    "homeTeam": "Murcia",
    "awayTeam": "Tortona"
  },
  {
    "matchId": "g_3_CxNQqG5l",
    "eventTime": "19.12. 18:00",
    "homeTeam": "Cholet",
    "awayTeam": "Tenerife"
  },
  {
    "matchId": "g_3_v1pmYwZB",
    "eventTime": "19.12. 18:00",
    "homeTeam": "Darussafaka",
    "awayTeam": "VEF Riga"
  },
  {
    "matchId": "g_3_SSJv71zD",
    "eventTime": "19.12. 18:00",
    "homeTeam": "Peristeri",
    "awayTeam": "Unicaja"
  },
  {
    "matchId": "g_3_l81uP6Xb",
    "eventTime": "19.12. 18:00",
    "homeTeam": "Strasbourg",
    "awayTeam": "Oldenburg"
  },
  {
    "matchId": "g_3_p4UZ7sL6",
    "eventTime": "19.12. 18:00",
    "homeTeam": "Szombathely",
    "awayTeam": "Le Mans"
  },
  {
    "matchId": "g_3_v1OHIbZO",
    "eventTime": "19.12. 18:30",
    "homeTeam": "Opava",
    "awayTeam": "Promitheas"
  },
  {
    "matchId": "g_3_t620srCP",
    "eventTime": "19.12. 18:30",
    "homeTeam": "Rytas",
    "awayTeam": "Dijon"
  },
  {
    "matchId": "g_3_Wzc3WxLL",
    "eventTime": "19.12. 20:00",
    "homeTeam": "Oostende",
    "awayTeam": "Pinar Karsiyaka"
  },
  {
    "matchId": "g_3_IqZKVfej",
    "eventTime": "20.12. 18:00",
    "homeTeam": "Hapoel Jerusalem",
    "awayTeam": "Benfica"
  },
  {
    "matchId": "g_3_z7OL5CBs",
    "eventTime": "20.12. 18:00",
    "homeTeam": "Igokea",
    "awayTeam": "Tortona"
  },
  {
    "matchId": "g_3_UTNP4WQm",
    "eventTime": "20.12. 18:00",
    "homeTeam": "Tofas",
    "awayTeam": "Murcia"
  },
  {
    "matchId": "g_3_db8CcFJK",
    "eventTime": "20.12. 18:30",
    "homeTeam": "PAOK",
    "awayTeam": "Galatasaray"
  },
  {
    "matchId": "g_3_KGZ4vzDr",
    "eventTime": "20.12. 20:00",
    "homeTeam": "Breogan",
    "awayTeam": "Bonn"
  },
  {
    "matchId": "g_3_2uP9wfSl",
    "eventTime": "20.12. 20:00",
    "homeTeam": "Hapoel Holon",
    "awayTeam": "Bursaspor"
  },
  {
    "matchId": "g_3_6FMbTlmp",
    "eventTime": "20.12. 20:30",
    "homeTeam": "Ludwigsburg",
    "awayTeam": "AEK Athens"
  },
  {
    "matchId": "g_3_0xM2S82j",
    "eventTime": "20.12. 20:30",
    "homeTeam": "Sassari",
    "awayTeam": "Szczecin"
  }
]