{
  "matchData": {
    "date": "31.03.2016 18:00",
    "home": {
      "name": "Lokomotiv Kuban",
      "image": "https://static.flashscore.com/res/image/data/tfzLgCzB-YNdc4gY7.png"
    },
    "away": {
      "name": "Unicaja",
      "image": "https://static.flashscore.com/res/image/data/OtLQp0xS-nNbG1eNf.png"
    },
    "result": {
      "home": "81",
      "away": "60"
    },
    "totalLocal": "81",
    "firstLocal": "18",
    "secondLocal": "21",
    "thirstLocal": "23",
    "fourthLocal": "19",
    "extraLocal": "",
    "totalAway": "60",
    "firstAway": "14",
    "secondAway": "21",
    "thirstAway": "20",
    "fourthAway": "5",
    "extraAway": ""
  },
  "statsPlayer": [
    {
      "name": "Kuzminskas M.",
      "stats": {
        "TEAM": "UNI",
        "PTS": "16",
        "REB": "3",
        "AST": "-",
        "MIN": "20:19",
        "FGM": "-",
        "FGA": "-",
        "2PM": "-",
        "2PA": "-",
        "3PM": "-",
        "3PA": "-",
        "FTM": "-",
        "FTA": "-",
        "+/-": "-",
        "OR": "1",
        "DR": "2",
        "PF": "2",
        "ST": "-",
        "TO": "2",
        "BS": "-",
        "BA": "-",
        "TFS": "-"
      }
    },
    {
      "name": "Delaney M.",
      "stats": {
        "TEAM": "LOK",
        "PTS": "15",
        "REB": "3",
        "AST": "10",
        "MIN": "35:26",
        "FGM": "-",
        "FGA": "-",
        "2PM": "-",
        "2PA": "-",
        "3PM": "-",
        "3PA": "-",
        "FTM": "-",
        "FTA": "-",
        "+/-": "-",
        "OR": "-",
        "DR": "3",
        "PF": "3",
        "ST": "-",
        "TO": "-",
        "BS": "-",
        "BA": "-",
        "TFS": "-"
      }
    },
    {
      "name": "Janning M.",
      "stats": {
        "TEAM": "LOK",
        "PTS": "15",
        "REB": "2",
        "AST": "4",
        "MIN": "25:29",
        "FGM": "-",
        "FGA": "-",
        "2PM": "-",
        "2PA": "-",
        "3PM": "-",
        "3PA": "-",
        "FTM": "-",
        "FTA": "-",
        "+/-": "-",
        "OR": "1",
        "DR": "1",
        "PF": "1",
        "ST": "-",
        "TO": "1",
        "BS": "-",
        "BA": "-",
        "TFS": "-"
      }
    },
    {
      "name": "Broekhoff R.",
      "stats": {
        "TEAM": "LOK",
        "PTS": "14",
        "REB": "-",
        "AST": "1",
        "MIN": "16:06",
        "FGM": "-",
        "FGA": "-",
        "2PM": "-",
        "2PA": "-",
        "3PM": "-",
        "3PA": "-",
        "FTM": "-",
        "FTA": "-",
        "+/-": "-",
        "OR": "-",
        "DR": "-",
        "PF": "3",
        "ST": "2",
        "TO": "-",
        "BS": "-",
        "BA": "-",
        "TFS": "-"
      }
    },
    {
      "name": "Claver V.",
      "stats": {
        "TEAM": "LOK",
        "PTS": "14",
        "REB": "5",
        "AST": "2",
        "MIN": "30:00",
        "FGM": "-",
        "FGA": "-",
        "2PM": "-",
        "2PA": "-",
        "3PM": "-",
        "3PA": "-",
        "FTM": "-",
        "FTA": "-",
        "+/-": "-",
        "OR": "1",
        "DR": "4",
        "PF": "3",
        "ST": "3",
        "TO": "1",
        "BS": "-",
        "BA": "-",
        "TFS": "-"
      }
    },
    {
      "name": "Randolph A.",
      "stats": {
        "TEAM": "LOK",
        "PTS": "10",
        "REB": "8",
        "AST": "1",
        "MIN": "21:10",
        "FGM": "-",
        "FGA": "-",
        "2PM": "-",
        "2PA": "-",
        "3PM": "-",
        "3PA": "-",
        "FTM": "-",
        "FTA": "-",
        "+/-": "-",
        "OR": "3",
        "DR": "5",
        "PF": "2",
        "ST": "1",
        "TO": "2",
        "BS": "-",
        "BA": "1",
        "TFS": "-"
      }
    },
    {
      "name": "Nedovic N.",
      "stats": {
        "TEAM": "UNI",
        "PTS": "9",
        "REB": "2",
        "AST": "2",
        "MIN": "23:02",
        "FGM": "-",
        "FGA": "-",
        "2PM": "-",
        "2PA": "-",
        "3PM": "-",
        "3PA": "-",
        "FTM": "-",
        "FTA": "-",
        "+/-": "-",
        "OR": "-",
        "DR": "2",
        "PF": "3",
        "ST": "-",
        "TO": "2",
        "BS": "-",
        "BA": "-",
        "TFS": "-"
      }
    },
    {
      "name": "Diez D.",
      "stats": {
        "TEAM": "UNI",
        "PTS": "7",
        "REB": "7",
        "AST": "-",
        "MIN": "21:49",
        "FGM": "-",
        "FGA": "-",
        "2PM": "-",
        "2PA": "-",
        "3PM": "-",
        "3PA": "-",
        "FTM": "-",
        "FTA": "-",
        "+/-": "-",
        "OR": "1",
        "DR": "6",
        "PF": "1",
        "ST": "1",
        "TO": "-",
        "BS": "-",
        "BA": "-",
        "TFS": "-"
      }
    },
    {
      "name": "Thomas W.",
      "stats": {
        "TEAM": "UNI",
        "PTS": "7",
        "REB": "7",
        "AST": "2",
        "MIN": "23:01",
        "FGM": "-",
        "FGA": "-",
        "2PM": "-",
        "2PA": "-",
        "3PM": "-",
        "3PA": "-",
        "FTM": "-",
        "FTA": "-",
        "+/-": "-",
        "OR": "3",
        "DR": "4",
        "PF": "-",
        "ST": "3",
        "TO": "2",
        "BS": "-",
        "BA": "-",
        "TFS": "-"
      }
    },
    {
      "name": "Jackson E.",
      "stats": {
        "TEAM": "UNI",
        "PTS": "6",
        "REB": "1",
        "AST": "1",
        "MIN": "14:50",
        "FGM": "-",
        "FGA": "-",
        "2PM": "-",
        "2PA": "-",
        "3PM": "-",
        "3PA": "-",
        "FTM": "-",
        "FTA": "-",
        "+/-": "-",
        "OR": "-",
        "DR": "1",
        "PF": "1",
        "ST": "-",
        "TO": "3",
        "BS": "-",
        "BA": "-",
        "TFS": "-"
      }
    },
    {
      "name": "Draper D.",
      "stats": {
        "TEAM": "LOK",
        "PTS": "5",
        "REB": "1",
        "AST": "4",
        "MIN": "21:15",
        "FGM": "-",
        "FGA": "-",
        "2PM": "-",
        "2PA": "-",
        "3PM": "-",
        "3PA": "-",
        "FTM": "-",
        "FTA": "-",
        "+/-": "-",
        "OR": "-",
        "DR": "1",
        "PF": "2",
        "ST": "2",
        "TO": "1",
        "BS": "-",
        "BA": "-",
        "TFS": "-"
      }
    },
    {
      "name": "Karahodzic K.",
      "stats": {
        "TEAM": "UNI",
        "PTS": "5",
        "REB": "-",
        "AST": "-",
        "MIN": "17:03",
        "FGM": "-",
        "FGA": "-",
        "2PM": "-",
        "2PA": "-",
        "3PM": "-",
        "3PA": "-",
        "FTM": "-",
        "FTA": "-",
        "+/-": "-",
        "OR": "-",
        "DR": "-",
        "PF": "1",
        "ST": "-",
        "TO": "1",
        "BS": "-",
        "BA": "-",
        "TFS": "-"
      }
    },
    {
      "name": "Singleton C.",
      "stats": {
        "TEAM": "LOK",
        "PTS": "5",
        "REB": "3",
        "AST": "1",
        "MIN": "27:17",
        "FGM": "-",
        "FGA": "-",
        "2PM": "-",
        "2PA": "-",
        "3PM": "-",
        "3PA": "-",
        "FTM": "-",
        "FTA": "-",
        "+/-": "-",
        "OR": "2",
        "DR": "1",
        "PF": "1",
        "ST": "2",
        "TO": "2",
        "BS": "-",
        "BA": "-",
        "TFS": "-"
      }
    },
    {
      "name": "Nelson D.",
      "stats": {
        "TEAM": "UNI",
        "PTS": "4",
        "REB": "2",
        "AST": "3",
        "MIN": "20:23",
        "FGM": "-",
        "FGA": "-",
        "2PM": "-",
        "2PA": "-",
        "3PM": "-",
        "3PA": "-",
        "FTM": "-",
        "FTA": "-",
        "+/-": "-",
        "OR": "-",
        "DR": "2",
        "PF": "1",
        "ST": "-",
        "TO": "2",
        "BS": "-",
        "BA": "1",
        "TFS": "-"
      }
    },
    {
      "name": "Suarez C.",
      "stats": {
        "TEAM": "UNI",
        "PTS": "4",
        "REB": "7",
        "AST": "2",
        "MIN": "19:11",
        "FGM": "-",
        "FGA": "-",
        "2PM": "-",
        "2PA": "-",
        "3PM": "-",
        "3PA": "-",
        "FTM": "-",
        "FTA": "-",
        "+/-": "-",
        "OR": "3",
        "DR": "4",
        "PF": "2",
        "ST": "-",
        "TO": "2",
        "BS": "-",
        "BA": "-",
        "TFS": "-"
      }
    },
    {
      "name": "Zubkov A.",
      "stats": {
        "TEAM": "LOK",
        "PTS": "3",
        "REB": "2",
        "AST": "1",
        "MIN": "10:00",
        "FGM": "-",
        "FGA": "-",
        "2PM": "-",
        "2PA": "-",
        "3PM": "-",
        "3PA": "-",
        "FTM": "-",
        "FTA": "-",
        "+/-": "-",
        "OR": "2",
        "DR": "-",
        "PF": "1",
        "ST": "-",
        "TO": "1",
        "BS": "-",
        "BA": "-",
        "TFS": "-"
      }
    },
    {
      "name": "Vazquez F.",
      "stats": {
        "TEAM": "UNI",
        "PTS": "2",
        "REB": "1",
        "AST": "-",
        "MIN": "20:45",
        "FGM": "-",
        "FGA": "-",
        "2PM": "-",
        "2PA": "-",
        "3PM": "-",
        "3PA": "-",
        "FTM": "-",
        "FTA": "-",
        "+/-": "-",
        "OR": "-",
        "DR": "1",
        "PF": "2",
        "ST": "-",
        "TO": "-",
        "BS": "1",
        "BA": "-",
        "TFS": "-"
      }
    },
    {
      "name": "Diaz A.",
      "stats": {
        "TEAM": "UNI",
        "PTS": "-",
        "REB": "-",
        "AST": "1",
        "MIN": "19:37",
        "FGM": "-",
        "FGA": "-",
        "2PM": "-",
        "2PA": "-",
        "3PM": "-",
        "3PA": "-",
        "FTM": "-",
        "FTA": "-",
        "+/-": "-",
        "OR": "-",
        "DR": "-",
        "PF": "2",
        "ST": "1",
        "TO": "3",
        "BS": "-",
        "BA": "-",
        "TFS": "-"
      }
    },
    {
      "name": "Voronov E.",
      "stats": {
        "TEAM": "LOK",
        "PTS": "-",
        "REB": "1",
        "AST": "1",
        "MIN": "13:17",
        "FGM": "-",
        "FGA": "-",
        "2PM": "-",
        "2PA": "-",
        "3PM": "-",
        "3PA": "-",
        "FTM": "-",
        "FTA": "-",
        "+/-": "-",
        "OR": "1",
        "DR": "-",
        "PF": "3",
        "ST": "-",
        "TO": "1",
        "BS": "1",
        "BA": "-",
        "TFS": "-"
      }
    }
  ],
  "statsMatch_all": [
    {
      "category": "Field Goals Attempted ",
      "homeValue": "59",
      "awayValue": "46",
      "homeChartWidth": "56%",
      "awayChartWidth": "44%"
    },
    {
      "category": "Field Goals Made ",
      "homeValue": "28",
      "awayValue": "21",
      "homeChartWidth": "57%",
      "awayChartWidth": "43%"
    },
    {
      "category": "Field Goals % ",
      "homeValue": "47.5%",
      "awayValue": "45.7%",
      "homeChartWidth": "50%",
      "awayChartWidth": "50%"
    },
    {
      "category": "2-Point Field G. Attempted ",
      "homeValue": "25",
      "awayValue": "23",
      "homeChartWidth": "52%",
      "awayChartWidth": "48%"
    },
    {
      "category": "2-Point Field Goals Made ",
      "homeValue": "13",
      "awayValue": "16",
      "homeChartWidth": "44%",
      "awayChartWidth": "56%"
    },
    {
      "category": "2-Point Field Goals % ",
      "homeValue": "52%",
      "awayValue": "69.6%",
      "homeChartWidth": "42%",
      "awayChartWidth": "58%"
    },
    {
      "category": "3-Point Field G. Attempted ",
      "homeValue": "34",
      "awayValue": "23",
      "homeChartWidth": "59%",
      "awayChartWidth": "41%"
    },
    {
      "category": "3-Point Field Goals Made ",
      "homeValue": "15",
      "awayValue": "5",
      "homeChartWidth": "75%",
      "awayChartWidth": "25%"
    },
    {
      "category": "3-Point Field Goals % ",
      "homeValue": "44.1%",
      "awayValue": "21.7%",
      "homeChartWidth": "67%",
      "awayChartWidth": "33%"
    },
    {
      "category": "Free Throws Attempted ",
      "homeValue": "14",
      "awayValue": "13",
      "homeChartWidth": "51%",
      "awayChartWidth": "49%"
    },
    {
      "category": "Free Throws Made ",
      "homeValue": "10",
      "awayValue": "13",
      "homeChartWidth": "43%",
      "awayChartWidth": "57%"
    },
    {
      "category": "Free Throws % ",
      "homeValue": "71.4%",
      "awayValue": "100%",
      "homeChartWidth": "41%",
      "awayChartWidth": "59%"
    },
    {
      "category": "Offensive Rebounds ",
      "homeValue": "10",
      "awayValue": "9",
      "homeChartWidth": "52%",
      "awayChartWidth": "48%"
    },
    {
      "category": "Defensive Rebounds ",
      "homeValue": "15",
      "awayValue": "24",
      "homeChartWidth": "38%",
      "awayChartWidth": "62%"
    },
    {
      "category": "Total Rebounds ",
      "homeValue": "25",
      "awayValue": "33",
      "homeChartWidth": "43%",
      "awayChartWidth": "57%"
    },
    {
      "category": "Assists ",
      "homeValue": "25",
      "awayValue": "11",
      "homeChartWidth": "69%",
      "awayChartWidth": "31%"
    },
    {
      "category": "Blocks ",
      "homeValue": "1",
      "awayValue": "1",
      "homeChartWidth": "50%",
      "awayChartWidth": "50%"
    },
    {
      "category": "Turnovers ",
      "homeValue": "9",
      "awayValue": "19",
      "homeChartWidth": "32%",
      "awayChartWidth": "68%"
    },
    {
      "category": "Steals ",
      "homeValue": "10",
      "awayValue": "5",
      "homeChartWidth": "66%",
      "awayChartWidth": "34%"
    },
    {
      "category": "Personal Fouls ",
      "homeValue": "19",
      "awayValue": "15",
      "homeChartWidth": "55%",
      "awayChartWidth": "45%"
    }
  ],
  "statsMatch_first": [
    {
      "category": "Field Goals Attempted ",
      "homeValue": "16",
      "awayValue": "14",
      "homeChartWidth": "53%",
      "awayChartWidth": "47%"
    },
    {
      "category": "Field Goals Made ",
      "homeValue": "6",
      "awayValue": "5",
      "homeChartWidth": "54%",
      "awayChartWidth": "46%"
    },
    {
      "category": "Field Goals % ",
      "homeValue": "37.5%",
      "awayValue": "35.7%",
      "homeChartWidth": "51%",
      "awayChartWidth": "49%"
    },
    {
      "category": "2-Point Field G. Attempted ",
      "homeValue": "10",
      "awayValue": "8",
      "homeChartWidth": "55%",
      "awayChartWidth": "45%"
    },
    {
      "category": "2-Point Field Goals Made ",
      "homeValue": "5",
      "awayValue": "5",
      "homeChartWidth": "50%",
      "awayChartWidth": "50%"
    },
    {
      "category": "2-Point Field Goals % ",
      "homeValue": "50%",
      "awayValue": "62.5%",
      "homeChartWidth": "44%",
      "awayChartWidth": "56%"
    },
    {
      "category": "3-Point Field G. Attempted ",
      "homeValue": "6",
      "awayValue": "6",
      "homeChartWidth": "50%",
      "awayChartWidth": "50%"
    },
    {
      "category": "3-Point Field Goals Made ",
      "homeValue": "1",
      "awayValue": "0",
      "homeChartWidth": "100%",
      "awayChartWidth": "0%"
    },
    {
      "category": "3-Point Field Goals % ",
      "homeValue": "16.7%",
      "awayValue": "0%",
      "homeChartWidth": "100%",
      "awayChartWidth": "0%"
    },
    {
      "category": "Free Throws Attempted ",
      "homeValue": "7",
      "awayValue": "4",
      "homeChartWidth": "63%",
      "awayChartWidth": "37%"
    },
    {
      "category": "Free Throws Made ",
      "homeValue": "5",
      "awayValue": "4",
      "homeChartWidth": "55%",
      "awayChartWidth": "45%"
    },
    {
      "category": "Free Throws % ",
      "homeValue": "71.4%",
      "awayValue": "100%",
      "homeChartWidth": "41%",
      "awayChartWidth": "59%"
    },
    {
      "category": "Offensive Rebounds ",
      "homeValue": "4",
      "awayValue": "3",
      "homeChartWidth": "57%",
      "awayChartWidth": "43%"
    },
    {
      "category": "Defensive Rebounds ",
      "homeValue": "6",
      "awayValue": "8",
      "homeChartWidth": "42%",
      "awayChartWidth": "58%"
    },
    {
      "category": "Total Rebounds ",
      "homeValue": "10",
      "awayValue": "11",
      "homeChartWidth": "47%",
      "awayChartWidth": "53%"
    },
    {
      "category": "Assists ",
      "homeValue": "6",
      "awayValue": "2",
      "homeChartWidth": "75%",
      "awayChartWidth": "25%"
    },
    {
      "category": "Blocks ",
      "homeValue": "1",
      "awayValue": "0",
      "homeChartWidth": "100%",
      "awayChartWidth": "0%"
    },
    {
      "category": "Turnovers ",
      "homeValue": "1",
      "awayValue": "2",
      "homeChartWidth": "33%",
      "awayChartWidth": "67%"
    },
    {
      "category": "Steals ",
      "homeValue": "1",
      "awayValue": "0",
      "homeChartWidth": "100%",
      "awayChartWidth": "0%"
    },
    {
      "category": "Personal Fouls ",
      "homeValue": "6",
      "awayValue": "5",
      "homeChartWidth": "54%",
      "awayChartWidth": "46%"
    }
  ],
  "statsMatch_second": [
    {
      "category": "Field Goals Attempted ",
      "homeValue": "15",
      "awayValue": "13",
      "homeChartWidth": "53%",
      "awayChartWidth": "47%"
    },
    {
      "category": "Field Goals Made ",
      "homeValue": "8",
      "awayValue": "9",
      "homeChartWidth": "47%",
      "awayChartWidth": "53%"
    },
    {
      "category": "Field Goals % ",
      "homeValue": "53.3%",
      "awayValue": "69.2%",
      "homeChartWidth": "43%",
      "awayChartWidth": "57%"
    },
    {
      "category": "2-Point Field G. Attempted ",
      "homeValue": "4",
      "awayValue": "7",
      "homeChartWidth": "36%",
      "awayChartWidth": "64%"
    },
    {
      "category": "2-Point Field Goals Made ",
      "homeValue": "3",
      "awayValue": "7",
      "homeChartWidth": "30%",
      "awayChartWidth": "70%"
    },
    {
      "category": "2-Point Field Goals % ",
      "homeValue": "75%",
      "awayValue": "100%",
      "homeChartWidth": "42%",
      "awayChartWidth": "58%"
    },
    {
      "category": "3-Point Field G. Attempted ",
      "homeValue": "11",
      "awayValue": "6",
      "homeChartWidth": "64%",
      "awayChartWidth": "36%"
    },
    {
      "category": "3-Point Field Goals Made ",
      "homeValue": "5",
      "awayValue": "2",
      "homeChartWidth": "71%",
      "awayChartWidth": "29%"
    },
    {
      "category": "3-Point Field Goals % ",
      "homeValue": "45.5%",
      "awayValue": "33.3%",
      "homeChartWidth": "57%",
      "awayChartWidth": "43%"
    },
    {
      "category": "Free Throws Attempted ",
      "homeValue": "0",
      "awayValue": "1",
      "homeChartWidth": "0%",
      "awayChartWidth": "100%"
    },
    {
      "category": "Free Throws Made ",
      "homeValue": "0",
      "awayValue": "1",
      "homeChartWidth": "0%",
      "awayChartWidth": "100%"
    },
    {
      "category": "Free Throws % ",
      "homeValue": "0%",
      "awayValue": "100%",
      "homeChartWidth": "0%",
      "awayChartWidth": "100%"
    },
    {
      "category": "Offensive Rebounds ",
      "homeValue": "2",
      "awayValue": "2",
      "homeChartWidth": "50%",
      "awayChartWidth": "50%"
    },
    {
      "category": "Defensive Rebounds ",
      "homeValue": "1",
      "awayValue": "5",
      "homeChartWidth": "16%",
      "awayChartWidth": "84%"
    },
    {
      "category": "Total Rebounds ",
      "homeValue": "3",
      "awayValue": "7",
      "homeChartWidth": "30%",
      "awayChartWidth": "70%"
    },
    {
      "category": "Assists ",
      "homeValue": "5",
      "awayValue": "4",
      "homeChartWidth": "55%",
      "awayChartWidth": "45%"
    },
    {
      "category": "Blocks ",
      "homeValue": "0",
      "awayValue": "0",
      "homeChartWidth": "50%",
      "awayChartWidth": "50%"
    },
    {
      "category": "Turnovers ",
      "homeValue": "3",
      "awayValue": "5",
      "homeChartWidth": "37%",
      "awayChartWidth": "63%"
    },
    {
      "category": "Steals ",
      "homeValue": "1",
      "awayValue": "3",
      "homeChartWidth": "25%",
      "awayChartWidth": "75%"
    },
    {
      "category": "Personal Fouls ",
      "homeValue": "2",
      "awayValue": "1",
      "homeChartWidth": "66%",
      "awayChartWidth": "34%"
    }
  ],
  "statsMtach_thirst": [
    {
      "category": "Field Goals Attempted ",
      "homeValue": "15",
      "awayValue": "11",
      "homeChartWidth": "57%",
      "awayChartWidth": "43%"
    },
    {
      "category": "Field Goals Made ",
      "homeValue": "8",
      "awayValue": "5",
      "homeChartWidth": "61%",
      "awayChartWidth": "39%"
    },
    {
      "category": "Field Goals % ",
      "homeValue": "53.3%",
      "awayValue": "45.5%",
      "homeChartWidth": "53%",
      "awayChartWidth": "47%"
    },
    {
      "category": "2-Point Field G. Attempted ",
      "homeValue": "5",
      "awayValue": "5",
      "homeChartWidth": "50%",
      "awayChartWidth": "50%"
    },
    {
      "category": "2-Point Field Goals Made ",
      "homeValue": "3",
      "awayValue": "3",
      "homeChartWidth": "50%",
      "awayChartWidth": "50%"
    },
    {
      "category": "2-Point Field Goals % ",
      "homeValue": "60%",
      "awayValue": "60%",
      "homeChartWidth": "50%",
      "awayChartWidth": "50%"
    },
    {
      "category": "3-Point Field G. Attempted ",
      "homeValue": "10",
      "awayValue": "6",
      "homeChartWidth": "62%",
      "awayChartWidth": "38%"
    },
    {
      "category": "3-Point Field Goals Made ",
      "homeValue": "5",
      "awayValue": "2",
      "homeChartWidth": "71%",
      "awayChartWidth": "29%"
    },
    {
      "category": "3-Point Field Goals % ",
      "homeValue": "50%",
      "awayValue": "33.3%",
      "homeChartWidth": "60%",
      "awayChartWidth": "40%"
    },
    {
      "category": "Free Throws Attempted ",
      "homeValue": "3",
      "awayValue": "8",
      "homeChartWidth": "27%",
      "awayChartWidth": "73%"
    },
    {
      "category": "Free Throws Made ",
      "homeValue": "2",
      "awayValue": "8",
      "homeChartWidth": "20%",
      "awayChartWidth": "80%"
    },
    {
      "category": "Free Throws % ",
      "homeValue": "66.7%",
      "awayValue": "100%",
      "homeChartWidth": "40%",
      "awayChartWidth": "60%"
    },
    {
      "category": "Offensive Rebounds ",
      "homeValue": "4",
      "awayValue": "2",
      "homeChartWidth": "66%",
      "awayChartWidth": "34%"
    },
    {
      "category": "Defensive Rebounds ",
      "homeValue": "4",
      "awayValue": "4",
      "homeChartWidth": "50%",
      "awayChartWidth": "50%"
    },
    {
      "category": "Total Rebounds ",
      "homeValue": "8",
      "awayValue": "6",
      "homeChartWidth": "57%",
      "awayChartWidth": "43%"
    },
    {
      "category": "Assists ",
      "homeValue": "7",
      "awayValue": "3",
      "homeChartWidth": "70%",
      "awayChartWidth": "30%"
    },
    {
      "category": "Blocks ",
      "homeValue": "0",
      "awayValue": "1",
      "homeChartWidth": "0%",
      "awayChartWidth": "100%"
    },
    {
      "category": "Turnovers ",
      "homeValue": "3",
      "awayValue": "3",
      "homeChartWidth": "50%",
      "awayChartWidth": "50%"
    },
    {
      "category": "Steals ",
      "homeValue": "3",
      "awayValue": "2",
      "homeChartWidth": "60%",
      "awayChartWidth": "40%"
    },
    {
      "category": "Personal Fouls ",
      "homeValue": "7",
      "awayValue": "4",
      "homeChartWidth": "63%",
      "awayChartWidth": "37%"
    }
  ],
  "statsMtach_four": [
    {
      "category": "Field Goals Attempted ",
      "homeValue": "13",
      "awayValue": "8",
      "homeChartWidth": "61%",
      "awayChartWidth": "39%"
    },
    {
      "category": "Field Goals Made ",
      "homeValue": "6",
      "awayValue": "2",
      "homeChartWidth": "75%",
      "awayChartWidth": "25%"
    },
    {
      "category": "Field Goals % ",
      "homeValue": "46.2%",
      "awayValue": "25%",
      "homeChartWidth": "64%",
      "awayChartWidth": "36%"
    },
    {
      "category": "2-Point Field G. Attempted ",
      "homeValue": "6",
      "awayValue": "3",
      "homeChartWidth": "66%",
      "awayChartWidth": "34%"
    },
    {
      "category": "2-Point Field Goals Made ",
      "homeValue": "2",
      "awayValue": "1",
      "homeChartWidth": "66%",
      "awayChartWidth": "34%"
    },
    {
      "category": "2-Point Field Goals % ",
      "homeValue": "33.3%",
      "awayValue": "33.3%",
      "homeChartWidth": "50%",
      "awayChartWidth": "50%"
    },
    {
      "category": "3-Point Field G. Attempted ",
      "homeValue": "7",
      "awayValue": "5",
      "homeChartWidth": "58%",
      "awayChartWidth": "42%"
    },
    {
      "category": "3-Point Field Goals Made ",
      "homeValue": "4",
      "awayValue": "1",
      "homeChartWidth": "80%",
      "awayChartWidth": "20%"
    },
    {
      "category": "3-Point Field Goals % ",
      "homeValue": "57.1%",
      "awayValue": "20%",
      "homeChartWidth": "74%",
      "awayChartWidth": "26%"
    },
    {
      "category": "Free Throws Attempted ",
      "homeValue": "4",
      "awayValue": "0",
      "homeChartWidth": "100%",
      "awayChartWidth": "0%"
    },
    {
      "category": "Free Throws Made ",
      "homeValue": "3",
      "awayValue": "0",
      "homeChartWidth": "100%",
      "awayChartWidth": "0%"
    },
    {
      "category": "Free Throws % ",
      "homeValue": "75%",
      "awayValue": "0%",
      "homeChartWidth": "100%",
      "awayChartWidth": "0%"
    },
    {
      "category": "Offensive Rebounds ",
      "homeValue": "0",
      "awayValue": "2",
      "homeChartWidth": "0%",
      "awayChartWidth": "100%"
    },
    {
      "category": "Defensive Rebounds ",
      "homeValue": "4",
      "awayValue": "7",
      "homeChartWidth": "36%",
      "awayChartWidth": "64%"
    },
    {
      "category": "Total Rebounds ",
      "homeValue": "4",
      "awayValue": "9",
      "homeChartWidth": "30%",
      "awayChartWidth": "70%"
    },
    {
      "category": "Assists ",
      "homeValue": "7",
      "awayValue": "2",
      "homeChartWidth": "77%",
      "awayChartWidth": "23%"
    },
    {
      "category": "Blocks ",
      "homeValue": "0",
      "awayValue": "0",
      "homeChartWidth": "50%",
      "awayChartWidth": "50%"
    },
    {
      "category": "Turnovers ",
      "homeValue": "2",
      "awayValue": "9",
      "homeChartWidth": "18%",
      "awayChartWidth": "82%"
    },
    {
      "category": "Steals ",
      "homeValue": "5",
      "awayValue": "0",
      "homeChartWidth": "100%",
      "awayChartWidth": "0%"
    },
    {
      "category": "Personal Fouls ",
      "homeValue": "4",
      "awayValue": "5",
      "homeChartWidth": "44%",
      "awayChartWidth": "56%"
    }
  ],
  "statsMtach_five": null,
  "pointByPoint": [
    {
      "score": "2-0"
    },
    {
      "score": "3-0"
    },
    {
      "score": "4-0"
    },
    {
      "score": "4-2"
    },
    {
      "score": "6-2"
    },
    {
      "score": "9-2"
    },
    {
      "score": "10-2"
    },
    {
      "score": "10-4"
    },
    {
      "score": "11-4"
    },
    {
      "score": "11-6"
    },
    {
      "score": "11-8"
    },
    {
      "score": "13-8"
    },
    {
      "score": "13-9"
    },
    {
      "score": "13-10"
    },
    {
      "score": "13-12"
    },
    {
      "score": "15-12"
    },
    {
      "score": "17-12"
    },
    {
      "score": "18-12"
    },
    {
      "score": "18-13"
    },
    {
      "score": "18-14"
    }
  ],
  "pointByPoint_first": [
    {
      "score": "18-16"
    },
    {
      "score": "18-18"
    },
    {
      "score": "20-18"
    },
    {
      "score": "20-21"
    },
    {
      "score": "23-21"
    },
    {
      "score": "23-23"
    },
    {
      "score": "23-24"
    },
    {
      "score": "26-24"
    },
    {
      "score": "29-24"
    },
    {
      "score": "32-24"
    },
    {
      "score": "32-26"
    },
    {
      "score": "34-26"
    },
    {
      "score": "34-28"
    },
    {
      "score": "34-30"
    },
    {
      "score": "34-33"
    },
    {
      "score": "37-33"
    },
    {
      "score": "37-35"
    },
    {
      "score": "39-35"
    }
  ],
  "pointByPoint_second": [
    {
      "score": "39-37"
    },
    {
      "score": "42-37"
    },
    {
      "score": "42-38"
    },
    {
      "score": "42-39"
    },
    {
      "score": "44-39"
    },
    {
      "score": "44-40"
    },
    {
      "score": "44-41"
    },
    {
      "score": "46-41"
    },
    {
      "score": "47-41"
    },
    {
      "score": "47-43"
    },
    {
      "score": "50-43"
    },
    {
      "score": "50-44"
    },
    {
      "score": "50-45"
    },
    {
      "score": "52-45"
    },
    {
      "score": "52-46"
    },
    {
      "score": "52-47"
    },
    {
      "score": "55-47"
    },
    {
      "score": "55-49"
    },
    {
      "score": "58-49"
    },
    {
      "score": "58-52"
    },
    {
      "score": "59-52"
    },
    {
      "score": "62-52"
    },
    {
      "score": "62-55"
    }
  ],
  "pointByPoint_thirst": [
    {
      "score": "62-57"
    },
    {
      "score": "64-57"
    },
    {
      "score": "66-57"
    },
    {
      "score": "69-57"
    },
    {
      "score": "70-57"
    },
    {
      "score": "71-57"
    },
    {
      "score": "72-57"
    },
    {
      "score": "72-60"
    },
    {
      "score": "75-60"
    },
    {
      "score": "78-60"
    },
    {
      "score": "81-60"
    }
  ]
}