{
  "matchData": {
    "date": "25.02.2016 19:00",
    "home": {
      "name": "Lokomotiv Kuban",
      "image": "https://static.flashscore.com/res/image/data/tfzLgCzB-YNdc4gY7.png"
    },
    "away": {
      "name": "Cedevita",
      "image": "https://static.flashscore.com/res/image/data/d8wWXnGG-nu8W1Id3.png"
    },
    "result": {
      "home": "87",
      "away": "63"
    },
    "totalLocal": "87",
    "firstLocal": "29",
    "secondLocal": "15",
    "thirstLocal": "26",
    "fourthLocal": "17",
    "extraLocal": "",
    "totalAway": "63",
    "firstAway": "12",
    "secondAway": "21",
    "thirstAway": "13",
    "fourthAway": "17",
    "extraAway": ""
  },
  "statsPlayer": [
    {
      "name": "Randolph A.",
      "stats": {
        "TEAM": "LOK",
        "PTS": "28",
        "REB": "13",
        "AST": "5",
        "MIN": "27:51",
        "FGM": "-",
        "FGA": "-",
        "2PM": "-",
        "2PA": "-",
        "3PM": "-",
        "3PA": "-",
        "FTM": "-",
        "FTA": "-",
        "+/-": "-",
        "OR": "4",
        "DR": "9",
        "PF": "2",
        "ST": "1",
        "TO": "2",
        "BS": "1",
        "BA": "-",
        "TFS": "-"
      }
    },
    {
      "name": "Broekhoff R.",
      "stats": {
        "TEAM": "LOK",
        "PTS": "14",
        "REB": "3",
        "AST": "2",
        "MIN": "23:10",
        "FGM": "-",
        "FGA": "-",
        "2PM": "-",
        "2PA": "-",
        "3PM": "-",
        "3PA": "-",
        "FTM": "-",
        "FTA": "-",
        "+/-": "-",
        "OR": "1",
        "DR": "2",
        "PF": "2",
        "ST": "-",
        "TO": "2",
        "BS": "-",
        "BA": "-",
        "TFS": "-"
      }
    },
    {
      "name": "Bilan M.",
      "stats": {
        "TEAM": "CED",
        "PTS": "11",
        "REB": "6",
        "AST": "1",
        "MIN": "23:54",
        "FGM": "-",
        "FGA": "-",
        "2PM": "-",
        "2PA": "-",
        "3PM": "-",
        "3PA": "-",
        "FTM": "-",
        "FTA": "-",
        "+/-": "-",
        "OR": "1",
        "DR": "5",
        "PF": "2",
        "ST": "1",
        "TO": "1",
        "BS": "-",
        "BA": "-",
        "TFS": "-"
      }
    },
    {
      "name": "Gordic N.",
      "stats": {
        "TEAM": "CED",
        "PTS": "9",
        "REB": "3",
        "AST": "3",
        "MIN": "20:44",
        "FGM": "-",
        "FGA": "-",
        "2PM": "-",
        "2PA": "-",
        "3PM": "-",
        "3PA": "-",
        "FTM": "-",
        "FTA": "-",
        "+/-": "-",
        "OR": "1",
        "DR": "2",
        "PF": "2",
        "ST": "1",
        "TO": "3",
        "BS": "-",
        "BA": "-",
        "TFS": "-"
      }
    },
    {
      "name": "Janning M.",
      "stats": {
        "TEAM": "LOK",
        "PTS": "9",
        "REB": "2",
        "AST": "1",
        "MIN": "22:38",
        "FGM": "-",
        "FGA": "-",
        "2PM": "-",
        "2PA": "-",
        "3PM": "-",
        "3PA": "-",
        "FTM": "-",
        "FTA": "-",
        "+/-": "-",
        "OR": "2",
        "DR": "-",
        "PF": "3",
        "ST": "-",
        "TO": "-",
        "BS": "-",
        "BA": "-",
        "TFS": "-"
      }
    },
    {
      "name": "Pilepic F.",
      "stats": {
        "TEAM": "CED",
        "PTS": "9",
        "REB": "1",
        "AST": "2",
        "MIN": "24:59",
        "FGM": "-",
        "FGA": "-",
        "2PM": "-",
        "2PA": "-",
        "3PM": "-",
        "3PA": "-",
        "FTM": "-",
        "FTA": "-",
        "+/-": "-",
        "OR": "-",
        "DR": "1",
        "PF": "2",
        "ST": "-",
        "TO": "1",
        "BS": "-",
        "BA": "-",
        "TFS": "-"
      }
    },
    {
      "name": "Bykov S.",
      "stats": {
        "TEAM": "LOK",
        "PTS": "8",
        "REB": "2",
        "AST": "-",
        "MIN": "13:35",
        "FGM": "-",
        "FGA": "-",
        "2PM": "-",
        "2PA": "-",
        "3PM": "-",
        "3PA": "-",
        "FTM": "-",
        "FTA": "-",
        "+/-": "-",
        "OR": "-",
        "DR": "2",
        "PF": "3",
        "ST": "-",
        "TO": "3",
        "BS": "-",
        "BA": "-",
        "TFS": "-"
      }
    },
    {
      "name": "Voronov E.",
      "stats": {
        "TEAM": "LOK",
        "PTS": "8",
        "REB": "-",
        "AST": "-",
        "MIN": "9:33",
        "FGM": "-",
        "FGA": "-",
        "2PM": "-",
        "2PA": "-",
        "3PM": "-",
        "3PA": "-",
        "FTM": "-",
        "FTA": "-",
        "+/-": "-",
        "OR": "-",
        "DR": "-",
        "PF": "1",
        "ST": "1",
        "TO": "-",
        "BS": "-",
        "BA": "-",
        "TFS": "-"
      }
    },
    {
      "name": "White J.",
      "stats": {
        "TEAM": "CED",
        "PTS": "8",
        "REB": "4",
        "AST": "-",
        "MIN": "21:34",
        "FGM": "-",
        "FGA": "-",
        "2PM": "-",
        "2PA": "-",
        "3PM": "-",
        "3PA": "-",
        "FTM": "-",
        "FTA": "-",
        "+/-": "-",
        "OR": "1",
        "DR": "3",
        "PF": "3",
        "ST": "-",
        "TO": "2",
        "BS": "-",
        "BA": "-",
        "TFS": "-"
      }
    },
    {
      "name": "Zoric L.",
      "stats": {
        "TEAM": "CED",
        "PTS": "6",
        "REB": "-",
        "AST": "1",
        "MIN": "11:53",
        "FGM": "-",
        "FGA": "-",
        "2PM": "-",
        "2PA": "-",
        "3PM": "-",
        "3PA": "-",
        "FTM": "-",
        "FTA": "-",
        "+/-": "-",
        "OR": "-",
        "DR": "-",
        "PF": "-",
        "ST": "1",
        "TO": "2",
        "BS": "-",
        "BA": "1",
        "TFS": "-"
      }
    },
    {
      "name": "Zubkov A.",
      "stats": {
        "TEAM": "LOK",
        "PTS": "6",
        "REB": "5",
        "AST": "1",
        "MIN": "16:13",
        "FGM": "-",
        "FGA": "-",
        "2PM": "-",
        "2PA": "-",
        "3PM": "-",
        "3PA": "-",
        "FTM": "-",
        "FTA": "-",
        "+/-": "-",
        "OR": "1",
        "DR": "4",
        "PF": "2",
        "ST": "1",
        "TO": "1",
        "BS": "-",
        "BA": "1",
        "TFS": "-"
      }
    },
    {
      "name": "Claver V.",
      "stats": {
        "TEAM": "LOK",
        "PTS": "5",
        "REB": "2",
        "AST": "-",
        "MIN": "23:47",
        "FGM": "-",
        "FGA": "-",
        "2PM": "-",
        "2PA": "-",
        "3PM": "-",
        "3PA": "-",
        "FTM": "-",
        "FTA": "-",
        "+/-": "-",
        "OR": "1",
        "DR": "1",
        "PF": "2",
        "ST": "2",
        "TO": "-",
        "BS": "1",
        "BA": "-",
        "TFS": "-"
      }
    },
    {
      "name": "Katic T.",
      "stats": {
        "TEAM": "CED",
        "PTS": "5",
        "REB": "1",
        "AST": "1",
        "MIN": "4:13",
        "FGM": "-",
        "FGA": "-",
        "2PM": "-",
        "2PA": "-",
        "3PM": "-",
        "3PA": "-",
        "FTM": "-",
        "FTA": "-",
        "+/-": "-",
        "OR": "-",
        "DR": "1",
        "PF": "1",
        "ST": "-",
        "TO": "-",
        "BS": "-",
        "BA": "-",
        "TFS": "-"
      }
    },
    {
      "name": "Walker H.",
      "stats": {
        "TEAM": "CED",
        "PTS": "5",
        "REB": "3",
        "AST": "-",
        "MIN": "18:45",
        "FGM": "-",
        "FGA": "-",
        "2PM": "-",
        "2PA": "-",
        "3PM": "-",
        "3PA": "-",
        "FTM": "-",
        "FTA": "-",
        "+/-": "-",
        "OR": "1",
        "DR": "2",
        "PF": "4",
        "ST": "-",
        "TO": "2",
        "BS": "-",
        "BA": "-",
        "TFS": "-"
      }
    },
    {
      "name": "Arapovic M.",
      "stats": {
        "TEAM": "CED",
        "PTS": "4",
        "REB": "3",
        "AST": "1",
        "MIN": "15:29",
        "FGM": "-",
        "FGA": "-",
        "2PM": "-",
        "2PA": "-",
        "3PM": "-",
        "3PA": "-",
        "FTM": "-",
        "FTA": "-",
        "+/-": "-",
        "OR": "1",
        "DR": "2",
        "PF": "3",
        "ST": "-",
        "TO": "-",
        "BS": "-",
        "BA": "1",
        "TFS": "-"
      }
    },
    {
      "name": "Delaney M.",
      "stats": {
        "TEAM": "LOK",
        "PTS": "4",
        "REB": "6",
        "AST": "10",
        "MIN": "31:07",
        "FGM": "-",
        "FGA": "-",
        "2PM": "-",
        "2PA": "-",
        "3PM": "-",
        "3PA": "-",
        "FTM": "-",
        "FTA": "-",
        "+/-": "-",
        "OR": "-",
        "DR": "6",
        "PF": "2",
        "ST": "2",
        "TO": "3",
        "BS": "-",
        "BA": "-",
        "TFS": "-"
      }
    },
    {
      "name": "Singleton C.",
      "stats": {
        "TEAM": "LOK",
        "PTS": "3",
        "REB": "2",
        "AST": "2",
        "MIN": "7:32",
        "FGM": "-",
        "FGA": "-",
        "2PM": "-",
        "2PA": "-",
        "3PM": "-",
        "3PA": "-",
        "FTM": "-",
        "FTA": "-",
        "+/-": "-",
        "OR": "1",
        "DR": "1",
        "PF": "2",
        "ST": "1",
        "TO": "-",
        "BS": "-",
        "BA": "-",
        "TFS": "-"
      }
    },
    {
      "name": "Draper D.",
      "stats": {
        "TEAM": "LOK",
        "PTS": "2",
        "REB": "3",
        "AST": "1",
        "MIN": "15:44",
        "FGM": "-",
        "FGA": "-",
        "2PM": "-",
        "2PA": "-",
        "3PM": "-",
        "3PA": "-",
        "FTM": "-",
        "FTA": "-",
        "+/-": "-",
        "OR": "-",
        "DR": "3",
        "PF": "3",
        "ST": "-",
        "TO": "2",
        "BS": "-",
        "BA": "-",
        "TFS": "-"
      }
    },
    {
      "name": "Mazalin L.",
      "stats": {
        "TEAM": "CED",
        "PTS": "2",
        "REB": "1",
        "AST": "-",
        "MIN": "7:20",
        "FGM": "-",
        "FGA": "-",
        "2PM": "-",
        "2PA": "-",
        "3PM": "-",
        "3PA": "-",
        "FTM": "-",
        "FTA": "-",
        "+/-": "-",
        "OR": "1",
        "DR": "-",
        "PF": "2",
        "ST": "-",
        "TO": "1",
        "BS": "-",
        "BA": "-",
        "TFS": "-"
      }
    },
    {
      "name": "Zganec K.",
      "stats": {
        "TEAM": "CED",
        "PTS": "2",
        "REB": "2",
        "AST": "-",
        "MIN": "9:59",
        "FGM": "-",
        "FGA": "-",
        "2PM": "-",
        "2PA": "-",
        "3PM": "-",
        "3PA": "-",
        "FTM": "-",
        "FTA": "-",
        "+/-": "-",
        "OR": "-",
        "DR": "2",
        "PF": "1",
        "ST": "1",
        "TO": "-",
        "BS": "1",
        "BA": "-",
        "TFS": "-"
      }
    },
    {
      "name": "Babic L.",
      "stats": {
        "TEAM": "CED",
        "PTS": "1",
        "REB": "3",
        "AST": "3",
        "MIN": "21:54",
        "FGM": "-",
        "FGA": "-",
        "2PM": "-",
        "2PA": "-",
        "3PM": "-",
        "3PA": "-",
        "FTM": "-",
        "FTA": "-",
        "+/-": "-",
        "OR": "1",
        "DR": "2",
        "PF": "3",
        "ST": "1",
        "TO": "1",
        "BS": "-",
        "BA": "-",
        "TFS": "-"
      }
    },
    {
      "name": "Pullen J.",
      "stats": {
        "TEAM": "CED",
        "PTS": "1",
        "REB": "2",
        "AST": "2",
        "MIN": "19:16",
        "FGM": "-",
        "FGA": "-",
        "2PM": "-",
        "2PA": "-",
        "3PM": "-",
        "3PA": "-",
        "FTM": "-",
        "FTA": "-",
        "+/-": "-",
        "OR": "1",
        "DR": "1",
        "PF": "1",
        "ST": "-",
        "TO": "4",
        "BS": "-",
        "BA": "-",
        "TFS": "-"
      }
    },
    {
      "name": "Balashov N.",
      "stats": {
        "TEAM": "LOK",
        "PTS": "-",
        "REB": "1",
        "AST": "2",
        "MIN": "4:37",
        "FGM": "-",
        "FGA": "-",
        "2PM": "-",
        "2PA": "-",
        "3PM": "-",
        "3PA": "-",
        "FTM": "-",
        "FTA": "-",
        "+/-": "-",
        "OR": "1",
        "DR": "-",
        "PF": "1",
        "ST": "-",
        "TO": "1",
        "BS": "-",
        "BA": "-",
        "TFS": "-"
      }
    },
    {
      "name": "Kolyushkin M.",
      "stats": {
        "TEAM": "LOK",
        "PTS": "-",
        "REB": "1",
        "AST": "1",
        "MIN": "4:13",
        "FGM": "-",
        "FGA": "-",
        "2PM": "-",
        "2PA": "-",
        "3PM": "-",
        "3PA": "-",
        "FTM": "-",
        "FTA": "-",
        "+/-": "-",
        "OR": "-",
        "DR": "1",
        "PF": "-",
        "ST": "1",
        "TO": "1",
        "BS": "-",
        "BA": "-",
        "TFS": "-"
      }
    }
  ],
  "statsMatch_all": [
    {
      "category": "Field Goals Attempted ",
      "homeValue": "64",
      "awayValue": "56",
      "homeChartWidth": "53%",
      "awayChartWidth": "47%"
    },
    {
      "category": "Field Goals Made ",
      "homeValue": "29",
      "awayValue": "21",
      "homeChartWidth": "57%",
      "awayChartWidth": "43%"
    },
    {
      "category": "Field Goals % ",
      "homeValue": "45.3%",
      "awayValue": "37.5%",
      "homeChartWidth": "54%",
      "awayChartWidth": "46%"
    },
    {
      "category": "2-Point Field G. Attempted ",
      "homeValue": "32",
      "awayValue": "35",
      "homeChartWidth": "47%",
      "awayChartWidth": "53%"
    },
    {
      "category": "2-Point Field Goals Made ",
      "homeValue": "17",
      "awayValue": "15",
      "homeChartWidth": "53%",
      "awayChartWidth": "47%"
    },
    {
      "category": "2-Point Field Goals % ",
      "homeValue": "53.1%",
      "awayValue": "42.9%",
      "homeChartWidth": "55%",
      "awayChartWidth": "45%"
    },
    {
      "category": "3-Point Field G. Attempted ",
      "homeValue": "32",
      "awayValue": "21",
      "homeChartWidth": "60%",
      "awayChartWidth": "40%"
    },
    {
      "category": "3-Point Field Goals Made ",
      "homeValue": "12",
      "awayValue": "6",
      "homeChartWidth": "66%",
      "awayChartWidth": "34%"
    },
    {
      "category": "3-Point Field Goals % ",
      "homeValue": "37.5%",
      "awayValue": "28.6%",
      "homeChartWidth": "56%",
      "awayChartWidth": "44%"
    },
    {
      "category": "Free Throws Attempted ",
      "homeValue": "21",
      "awayValue": "24",
      "homeChartWidth": "46%",
      "awayChartWidth": "54%"
    },
    {
      "category": "Free Throws Made ",
      "homeValue": "17",
      "awayValue": "15",
      "homeChartWidth": "53%",
      "awayChartWidth": "47%"
    },
    {
      "category": "Free Throws % ",
      "homeValue": "81%",
      "awayValue": "62.5%",
      "homeChartWidth": "56%",
      "awayChartWidth": "44%"
    },
    {
      "category": "Offensive Rebounds ",
      "homeValue": "12",
      "awayValue": "9",
      "homeChartWidth": "57%",
      "awayChartWidth": "43%"
    },
    {
      "category": "Defensive Rebounds ",
      "homeValue": "30",
      "awayValue": "24",
      "homeChartWidth": "55%",
      "awayChartWidth": "45%"
    },
    {
      "category": "Total Rebounds ",
      "homeValue": "42",
      "awayValue": "33",
      "homeChartWidth": "56%",
      "awayChartWidth": "44%"
    },
    {
      "category": "Assists ",
      "homeValue": "25",
      "awayValue": "14",
      "homeChartWidth": "64%",
      "awayChartWidth": "36%"
    },
    {
      "category": "Blocks ",
      "homeValue": "2",
      "awayValue": "1",
      "homeChartWidth": "66%",
      "awayChartWidth": "34%"
    },
    {
      "category": "Turnovers ",
      "homeValue": "15",
      "awayValue": "17",
      "homeChartWidth": "46%",
      "awayChartWidth": "54%"
    },
    {
      "category": "Steals ",
      "homeValue": "9",
      "awayValue": "5",
      "homeChartWidth": "64%",
      "awayChartWidth": "36%"
    },
    {
      "category": "Personal Fouls ",
      "homeValue": "23",
      "awayValue": "24",
      "homeChartWidth": "48%",
      "awayChartWidth": "52%"
    }
  ],
  "statsMatch_first": [
    {
      "category": "Field Goals Attempted ",
      "homeValue": "15",
      "awayValue": "15",
      "homeChartWidth": "50%",
      "awayChartWidth": "50%"
    },
    {
      "category": "Field Goals Made ",
      "homeValue": "7",
      "awayValue": "5",
      "homeChartWidth": "58%",
      "awayChartWidth": "42%"
    },
    {
      "category": "Field Goals % ",
      "homeValue": "46.7%",
      "awayValue": "33.3%",
      "homeChartWidth": "58%",
      "awayChartWidth": "42%"
    },
    {
      "category": "2-Point Field G. Attempted ",
      "homeValue": "5",
      "awayValue": "11",
      "homeChartWidth": "31%",
      "awayChartWidth": "69%"
    },
    {
      "category": "2-Point Field Goals Made ",
      "homeValue": "2",
      "awayValue": "5",
      "homeChartWidth": "28%",
      "awayChartWidth": "72%"
    },
    {
      "category": "2-Point Field Goals % ",
      "homeValue": "40%",
      "awayValue": "45.5%",
      "homeChartWidth": "46%",
      "awayChartWidth": "54%"
    },
    {
      "category": "3-Point Field G. Attempted ",
      "homeValue": "10",
      "awayValue": "4",
      "homeChartWidth": "71%",
      "awayChartWidth": "29%"
    },
    {
      "category": "3-Point Field Goals Made ",
      "homeValue": "5",
      "awayValue": "0",
      "homeChartWidth": "100%",
      "awayChartWidth": "0%"
    },
    {
      "category": "3-Point Field Goals % ",
      "homeValue": "50%",
      "awayValue": "0%",
      "homeChartWidth": "100%",
      "awayChartWidth": "0%"
    },
    {
      "category": "Free Throws Attempted ",
      "homeValue": "13",
      "awayValue": "4",
      "homeChartWidth": "76%",
      "awayChartWidth": "24%"
    },
    {
      "category": "Free Throws Made ",
      "homeValue": "10",
      "awayValue": "2",
      "homeChartWidth": "83%",
      "awayChartWidth": "17%"
    },
    {
      "category": "Free Throws % ",
      "homeValue": "76.9%",
      "awayValue": "50%",
      "homeChartWidth": "60%",
      "awayChartWidth": "40%"
    },
    {
      "category": "Offensive Rebounds ",
      "homeValue": "3",
      "awayValue": "2",
      "homeChartWidth": "60%",
      "awayChartWidth": "40%"
    },
    {
      "category": "Defensive Rebounds ",
      "homeValue": "9",
      "awayValue": "6",
      "homeChartWidth": "60%",
      "awayChartWidth": "40%"
    },
    {
      "category": "Total Rebounds ",
      "homeValue": "12",
      "awayValue": "8",
      "homeChartWidth": "60%",
      "awayChartWidth": "40%"
    },
    {
      "category": "Assists ",
      "homeValue": "7",
      "awayValue": "1",
      "homeChartWidth": "87%",
      "awayChartWidth": "13%"
    },
    {
      "category": "Blocks ",
      "homeValue": "0",
      "awayValue": "0",
      "homeChartWidth": "50%",
      "awayChartWidth": "50%"
    },
    {
      "category": "Turnovers ",
      "homeValue": "3",
      "awayValue": "4",
      "homeChartWidth": "42%",
      "awayChartWidth": "58%"
    },
    {
      "category": "Steals ",
      "homeValue": "2",
      "awayValue": "2",
      "homeChartWidth": "50%",
      "awayChartWidth": "50%"
    },
    {
      "category": "Personal Fouls ",
      "homeValue": "5",
      "awayValue": "9",
      "homeChartWidth": "35%",
      "awayChartWidth": "65%"
    }
  ],
  "statsMatch_second": [
    {
      "category": "Field Goals Attempted ",
      "homeValue": "17",
      "awayValue": "16",
      "homeChartWidth": "51%",
      "awayChartWidth": "49%"
    },
    {
      "category": "Field Goals Made ",
      "homeValue": "6",
      "awayValue": "7",
      "homeChartWidth": "46%",
      "awayChartWidth": "54%"
    },
    {
      "category": "Field Goals % ",
      "homeValue": "35.3%",
      "awayValue": "43.8%",
      "homeChartWidth": "44%",
      "awayChartWidth": "56%"
    },
    {
      "category": "2-Point Field G. Attempted ",
      "homeValue": "7",
      "awayValue": "10",
      "homeChartWidth": "41%",
      "awayChartWidth": "59%"
    },
    {
      "category": "2-Point Field Goals Made ",
      "homeValue": "3",
      "awayValue": "5",
      "homeChartWidth": "37%",
      "awayChartWidth": "63%"
    },
    {
      "category": "2-Point Field Goals % ",
      "homeValue": "42.9%",
      "awayValue": "50%",
      "homeChartWidth": "46%",
      "awayChartWidth": "54%"
    },
    {
      "category": "3-Point Field G. Attempted ",
      "homeValue": "10",
      "awayValue": "6",
      "homeChartWidth": "62%",
      "awayChartWidth": "38%"
    },
    {
      "category": "3-Point Field Goals Made ",
      "homeValue": "3",
      "awayValue": "2",
      "homeChartWidth": "60%",
      "awayChartWidth": "40%"
    },
    {
      "category": "3-Point Field Goals % ",
      "homeValue": "30%",
      "awayValue": "33.3%",
      "homeChartWidth": "47%",
      "awayChartWidth": "53%"
    },
    {
      "category": "Free Throws Attempted ",
      "homeValue": "0",
      "awayValue": "6",
      "homeChartWidth": "0%",
      "awayChartWidth": "100%"
    },
    {
      "category": "Free Throws Made ",
      "homeValue": "0",
      "awayValue": "5",
      "homeChartWidth": "0%",
      "awayChartWidth": "100%"
    },
    {
      "category": "Free Throws % ",
      "homeValue": "0%",
      "awayValue": "83.3%",
      "homeChartWidth": "0%",
      "awayChartWidth": "100%"
    },
    {
      "category": "Offensive Rebounds ",
      "homeValue": "3",
      "awayValue": "3",
      "homeChartWidth": "50%",
      "awayChartWidth": "50%"
    },
    {
      "category": "Defensive Rebounds ",
      "homeValue": "6",
      "awayValue": "8",
      "homeChartWidth": "42%",
      "awayChartWidth": "58%"
    },
    {
      "category": "Total Rebounds ",
      "homeValue": "9",
      "awayValue": "11",
      "homeChartWidth": "45%",
      "awayChartWidth": "55%"
    },
    {
      "category": "Assists ",
      "homeValue": "4",
      "awayValue": "6",
      "homeChartWidth": "40%",
      "awayChartWidth": "60%"
    },
    {
      "category": "Blocks ",
      "homeValue": "1",
      "awayValue": "0",
      "homeChartWidth": "100%",
      "awayChartWidth": "0%"
    },
    {
      "category": "Turnovers ",
      "homeValue": "4",
      "awayValue": "3",
      "homeChartWidth": "57%",
      "awayChartWidth": "43%"
    },
    {
      "category": "Steals ",
      "homeValue": "0",
      "awayValue": "0",
      "homeChartWidth": "50%",
      "awayChartWidth": "50%"
    },
    {
      "category": "Personal Fouls ",
      "homeValue": "7",
      "awayValue": "2",
      "homeChartWidth": "77%",
      "awayChartWidth": "23%"
    }
  ],
  "statsMtach_thirst": [
    {
      "category": "Field Goals Attempted ",
      "homeValue": "17",
      "awayValue": "13",
      "homeChartWidth": "56%",
      "awayChartWidth": "44%"
    },
    {
      "category": "Field Goals Made ",
      "homeValue": "9",
      "awayValue": "4",
      "homeChartWidth": "69%",
      "awayChartWidth": "31%"
    },
    {
      "category": "Field Goals % ",
      "homeValue": "52.9%",
      "awayValue": "30.8%",
      "homeChartWidth": "63%",
      "awayChartWidth": "37%"
    },
    {
      "category": "2-Point Field G. Attempted ",
      "homeValue": "12",
      "awayValue": "9",
      "homeChartWidth": "57%",
      "awayChartWidth": "43%"
    },
    {
      "category": "2-Point Field Goals Made ",
      "homeValue": "7",
      "awayValue": "3",
      "homeChartWidth": "70%",
      "awayChartWidth": "30%"
    },
    {
      "category": "2-Point Field Goals % ",
      "homeValue": "58.3%",
      "awayValue": "33.3%",
      "homeChartWidth": "63%",
      "awayChartWidth": "37%"
    },
    {
      "category": "3-Point Field G. Attempted ",
      "homeValue": "5",
      "awayValue": "4",
      "homeChartWidth": "55%",
      "awayChartWidth": "45%"
    },
    {
      "category": "3-Point Field Goals Made ",
      "homeValue": "2",
      "awayValue": "1",
      "homeChartWidth": "66%",
      "awayChartWidth": "34%"
    },
    {
      "category": "3-Point Field Goals % ",
      "homeValue": "40%",
      "awayValue": "25%",
      "homeChartWidth": "61%",
      "awayChartWidth": "39%"
    },
    {
      "category": "Free Throws Attempted ",
      "homeValue": "7",
      "awayValue": "6",
      "homeChartWidth": "53%",
      "awayChartWidth": "47%"
    },
    {
      "category": "Free Throws Made ",
      "homeValue": "6",
      "awayValue": "4",
      "homeChartWidth": "60%",
      "awayChartWidth": "40%"
    },
    {
      "category": "Free Throws % ",
      "homeValue": "85.7%",
      "awayValue": "66.7%",
      "homeChartWidth": "56%",
      "awayChartWidth": "44%"
    },
    {
      "category": "Offensive Rebounds ",
      "homeValue": "2",
      "awayValue": "2",
      "homeChartWidth": "50%",
      "awayChartWidth": "50%"
    },
    {
      "category": "Defensive Rebounds ",
      "homeValue": "8",
      "awayValue": "5",
      "homeChartWidth": "61%",
      "awayChartWidth": "39%"
    },
    {
      "category": "Total Rebounds ",
      "homeValue": "10",
      "awayValue": "7",
      "homeChartWidth": "58%",
      "awayChartWidth": "42%"
    },
    {
      "category": "Assists ",
      "homeValue": "8",
      "awayValue": "3",
      "homeChartWidth": "72%",
      "awayChartWidth": "28%"
    },
    {
      "category": "Blocks ",
      "homeValue": "1",
      "awayValue": "0",
      "homeChartWidth": "100%",
      "awayChartWidth": "0%"
    },
    {
      "category": "Turnovers ",
      "homeValue": "3",
      "awayValue": "7",
      "homeChartWidth": "30%",
      "awayChartWidth": "70%"
    },
    {
      "category": "Steals ",
      "homeValue": "5",
      "awayValue": "0",
      "homeChartWidth": "100%",
      "awayChartWidth": "0%"
    },
    {
      "category": "Personal Fouls ",
      "homeValue": "4",
      "awayValue": "9",
      "homeChartWidth": "30%",
      "awayChartWidth": "70%"
    }
  ],
  "statsMtach_four": [
    {
      "category": "Field Goals Attempted ",
      "homeValue": "15",
      "awayValue": "12",
      "homeChartWidth": "55%",
      "awayChartWidth": "45%"
    },
    {
      "category": "Field Goals Made ",
      "homeValue": "7",
      "awayValue": "5",
      "homeChartWidth": "58%",
      "awayChartWidth": "42%"
    },
    {
      "category": "Field Goals % ",
      "homeValue": "46.7%",
      "awayValue": "41.7%",
      "homeChartWidth": "52%",
      "awayChartWidth": "48%"
    },
    {
      "category": "2-Point Field G. Attempted ",
      "homeValue": "8",
      "awayValue": "5",
      "homeChartWidth": "61%",
      "awayChartWidth": "39%"
    },
    {
      "category": "2-Point Field Goals Made ",
      "homeValue": "5",
      "awayValue": "2",
      "homeChartWidth": "71%",
      "awayChartWidth": "29%"
    },
    {
      "category": "2-Point Field Goals % ",
      "homeValue": "62.5%",
      "awayValue": "40%",
      "homeChartWidth": "60%",
      "awayChartWidth": "40%"
    },
    {
      "category": "3-Point Field G. Attempted ",
      "homeValue": "7",
      "awayValue": "7",
      "homeChartWidth": "50%",
      "awayChartWidth": "50%"
    },
    {
      "category": "3-Point Field Goals Made ",
      "homeValue": "2",
      "awayValue": "3",
      "homeChartWidth": "40%",
      "awayChartWidth": "60%"
    },
    {
      "category": "3-Point Field Goals % ",
      "homeValue": "28.6%",
      "awayValue": "42.9%",
      "homeChartWidth": "40%",
      "awayChartWidth": "60%"
    },
    {
      "category": "Free Throws Attempted ",
      "homeValue": "1",
      "awayValue": "8",
      "homeChartWidth": "11%",
      "awayChartWidth": "89%"
    },
    {
      "category": "Free Throws Made ",
      "homeValue": "1",
      "awayValue": "4",
      "homeChartWidth": "20%",
      "awayChartWidth": "80%"
    },
    {
      "category": "Free Throws % ",
      "homeValue": "100%",
      "awayValue": "50%",
      "homeChartWidth": "66%",
      "awayChartWidth": "34%"
    },
    {
      "category": "Offensive Rebounds ",
      "homeValue": "4",
      "awayValue": "2",
      "homeChartWidth": "66%",
      "awayChartWidth": "34%"
    },
    {
      "category": "Defensive Rebounds ",
      "homeValue": "7",
      "awayValue": "5",
      "homeChartWidth": "58%",
      "awayChartWidth": "42%"
    },
    {
      "category": "Total Rebounds ",
      "homeValue": "11",
      "awayValue": "7",
      "homeChartWidth": "61%",
      "awayChartWidth": "39%"
    },
    {
      "category": "Assists ",
      "homeValue": "6",
      "awayValue": "4",
      "homeChartWidth": "60%",
      "awayChartWidth": "40%"
    },
    {
      "category": "Blocks ",
      "homeValue": "0",
      "awayValue": "1",
      "homeChartWidth": "0%",
      "awayChartWidth": "100%"
    },
    {
      "category": "Turnovers ",
      "homeValue": "5",
      "awayValue": "3",
      "homeChartWidth": "62%",
      "awayChartWidth": "38%"
    },
    {
      "category": "Steals ",
      "homeValue": "2",
      "awayValue": "3",
      "homeChartWidth": "40%",
      "awayChartWidth": "60%"
    },
    {
      "category": "Personal Fouls ",
      "homeValue": "7",
      "awayValue": "4",
      "homeChartWidth": "63%",
      "awayChartWidth": "37%"
    }
  ],
  "statsMtach_five": null,
  "pointByPoint": [
    {
      "score": "0-1"
    },
    {
      "score": "3-1"
    },
    {
      "score": "4-1"
    },
    {
      "score": "5-1"
    },
    {
      "score": "8-1"
    },
    {
      "score": "8-3"
    },
    {
      "score": "10-3"
    },
    {
      "score": "11-3"
    },
    {
      "score": "11-5"
    },
    {
      "score": "11-7"
    },
    {
      "score": "12-7"
    },
    {
      "score": "13-7"
    },
    {
      "score": "14-7"
    },
    {
      "score": "17-7"
    },
    {
      "score": "18-7"
    },
    {
      "score": "19-7"
    },
    {
      "score": "19-9"
    },
    {
      "score": "22-9"
    },
    {
      "score": "23-9"
    },
    {
      "score": "24-9"
    },
    {
      "score": "24-11"
    },
    {
      "score": "27-11"
    },
    {
      "score": "29-11"
    },
    {
      "score": "29-12"
    }
  ],
  "pointByPoint_first": [
    {
      "score": "29-14"
    },
    {
      "score": "32-14"
    },
    {
      "score": "32-15"
    },
    {
      "score": "35-15"
    },
    {
      "score": "35-18"
    },
    {
      "score": "35-19"
    },
    {
      "score": "35-20"
    },
    {
      "score": "37-20"
    },
    {
      "score": "37-23"
    },
    {
      "score": "37-25"
    },
    {
      "score": "40-25"
    },
    {
      "score": "42-25"
    },
    {
      "score": "42-27"
    },
    {
      "score": "44-27"
    },
    {
      "score": "44-29"
    },
    {
      "score": "44-30"
    },
    {
      "score": "44-31"
    },
    {
      "score": "44-33"
    }
  ],
  "pointByPoint_second": [
    {
      "score": "47-33"
    },
    {
      "score": "49-33"
    },
    {
      "score": "51-33"
    },
    {
      "score": "51-34"
    },
    {
      "score": "51-35"
    },
    {
      "score": "51-37"
    },
    {
      "score": "53-37"
    },
    {
      "score": "56-37"
    },
    {
      "score": "58-37"
    },
    {
      "score": "59-37"
    },
    {
      "score": "59-39"
    },
    {
      "score": "61-39"
    },
    {
      "score": "63-39"
    },
    {
      "score": "63-41"
    },
    {
      "score": "65-41"
    },
    {
      "score": "66-41"
    },
    {
      "score": "67-41"
    },
    {
      "score": "68-41"
    },
    {
      "score": "70-41"
    },
    {
      "score": "70-42"
    },
    {
      "score": "70-43"
    },
    {
      "score": "70-46"
    }
  ],
  "pointByPoint_thirst": [
    {
      "score": "70-49"
    },
    {
      "score": "73-49"
    },
    {
      "score": "73-52"
    },
    {
      "score": "76-52"
    },
    {
      "score": "76-53"
    },
    {
      "score": "76-54"
    },
    {
      "score": "76-55"
    },
    {
      "score": "78-55"
    },
    {
      "score": "78-58"
    },
    {
      "score": "80-58"
    },
    {
      "score": "81-58"
    },
    {
      "score": "83-58"
    },
    {
      "score": "83-60"
    },
    {
      "score": "85-60"
    },
    {
      "score": "85-62"
    },
    {
      "score": "85-63"
    },
    {
      "score": "87-63"
    }
  ]
}